threadsafe_json_dict/__init__.py
threadsafe_json_dict/core.py
threadsafe_json_dict-0.2.0.dist-info/licenses/LICENSE
threadsafe_json_dict-0.2.0.dist-info/METADATA
threadsafe_json_dict-0.2.0.dist-info/WHEEL
threadsafe_json_dict-0.2.0.dist-info/top_level.txt
threadsafe_json_dict-0.2.0.dist-info/RECORD
