Metadata-Version: 2.4
Name: threadsafe-json-dict
Version: 0.2.0
Summary: スレッドセーフなJSON保存機能付き辞書（Python 3.10+対応、自前実装）
Author-email: Your Name <your.email@example.com>
Maintainer-email: Your Name <your.email@example.com>
License-Expression: MIT
Project-URL: Homepage, https://github.com/yourusername/threadsafe-json-dict
Project-URL: Repository, https://github.com/yourusername/threadsafe-json-dict
Project-URL: Issues, https://github.com/yourusername/threadsafe-json-dict/issues
Project-URL: Bug Reports, https://github.com/yourusername/threadsafe-json-dict/issues
Project-URL: Source, https://github.com/yourusername/threadsafe-json-dict
Keywords: json,dict,cache,threadsafe,persistent,storage
Classifier: Development Status :: 4 - Beta
Classifier: Intended Audience :: Developers
Classifier: Operating System :: OS Independent
Classifier: Programming Language :: Python :: 3
Classifier: Programming Language :: Python :: 3.10
Classifier: Programming Language :: Python :: 3.11
Classifier: Programming Language :: Python :: 3.12
Classifier: Topic :: Software Development :: Libraries :: Python Modules
Classifier: Topic :: Database
Classifier: Topic :: System :: Archiving
Requires-Python: >=3.10
License-File: LICENSE
Provides-Extra: dev
Requires-Dist: pytest>=7.0; extra == "dev"
Requires-Dist: pytest-cov>=4.0; extra == "dev"
Requires-Dist: black>=23.0; extra == "dev"
Requires-Dist: ruff>=0.1.0; extra == "dev"
Requires-Dist: mypy>=1.0; extra == "dev"
Dynamic: license-file
